[
  {
    "id": "muscle_origin_insertion_001",
    "correctAnswer": "Rectus femoris",
    "question": "Which of the following muscles originates on the anterior inferior iliac spine (AIIS)?",
    "options": [
      "Rectus femoris",
      "Sartorius",
      "Iliacus",
      "Tensor fasciae latae"
    ],
    "topics": ["anatomy", "insertions", "muscle_origin_insertion"],
    "short_explanation": null,
    "long_explanation": null,
    "clinical_application": null,
    "source_reference": "Trail Guide to the Body",
    "filepath": "src/data/questions/anatomy/insertions/muscle_origin_insertion.json",
    "question_type": "multiple_choice",
    "difficulty": "Medium",
    "difficulty_rating": 3,
    "difficulty_adjustment": null,
    "relevance_score": null,
    "created_at": null,
    "updated_at": null,
    "tags": [
      "rectus femoris",
      "AIIS",
      "origin"
    ],
    "keywords": [
      "anterior inferior iliac spine",
      "hip flexion",
      "quadriceps"
    ],
    "synonyms": null
  },
  {
    "id": "muscle_origin_insertion_002",
    "correctAnswer": "Mastoid process of the temporal bone",
    "question": "What is the insertion point of the sternocleidomastoid muscle?",
    "options": [
      "Acromion and clavicle",
      "Styloid process of the temporal bone",
      "Mastoid process of the temporal bone",
      "Angle of the mandible"
    ],
    "topics": ["anatomy", "insertions", "muscle_origin_insertion"],
    "short_explanation": null,
    "long_explanation": null,
    "clinical_application": null,
    "source_reference": "Gray’s Anatomy",
    "filepath": "src/data/questions/anatomy/insertions/muscle_origin_insertion.json",
    "question_type": "multiple_choice",
    "difficulty": "Easy",
    "difficulty_rating": 2,
    "difficulty_adjustment": null,
    "relevance_score": null,
    "created_at": null,
    "updated_at": null,
    "tags": [
      "SCM",
      "insertion",
      "mastoid"
    ],
    "keywords": [
      "sternocleidomastoid",
      "mastoid process",
      "head movement"
    ],
    "synonyms": null
  },
  {
    "id": "muscle_origin_insertion_003",
    "correctAnswer": "Greater trochanter of the femur",
    "question": "The gluteus medius inserts on which bony landmark?",
    "options": [
      "Greater trochanter of the femur",
      "Lesser trochanter of the femur",
      "Iliac crest",
      "Ischial spine"
    ],
    "topics": ["anatomy", "insertions", "muscle_origin_insertion"],
    "short_explanation": null,
    "long_explanation": null,
    "clinical_application": null,
    "source_reference": "Kinesiology of the Musculoskeletal System",
    "filepath": "src/data/questions/anatomy/insertions/muscle_origin_insertion.json",
    "question_type": "multiple_choice",
    "difficulty": "Medium",
    "difficulty_rating": 3,
    "difficulty_adjustment": null,
    "relevance_score": null,
    "created_at": null,
    "updated_at": null,
    "tags": [
      "gluteus medius",
      "insertion",
      "greater trochanter"
    ],
    "keywords": [
      "hip abductor",
      "pelvic stability",
      "hip joint"
    ],
    "synonyms": null
  },
  {
    "id": "muscle_origin_insertion_004",
    "correctAnswer": "Latissimus dorsi",
    "question": "Which muscle originates on the spinous processes of T7–L5 and inserts on the intertubercular groove of the humerus?",
    "options": [
      "Trapezius",
      "Latissimus dorsi",
      "Teres major",
      "Rhomboid major"
    ],
    "topics": ["anatomy", "insertions", "muscle_origin_insertion"],
    "short_explanation": null,
    "long_explanation": null,
    "clinical_application": null,
    "source_reference": "Netter’s Atlas of Human Anatomy",
    "filepath": "src/data/questions/anatomy/insertions/muscle_origin_insertion.json",
    "question_type": "multiple_choice",
    "difficulty": "Medium",
    "difficulty_rating": 4,
    "difficulty_adjustment": null,
    "relevance_score": null,
    "created_at": null,
    "updated_at": null,
    "tags": [
      "latissimus dorsi",
      "origin",
      "insertion"
    ],
    "keywords": [
      "T7–L5",
      "intertubercular groove",
      "shoulder movement"
    ],
    "synonyms": null
  },
  {
    "id": "muscle_origin_insertion_005",
    "correctAnswer": "Brachialis",
    "question": "Which muscle inserts on the coronoid process and tuberosity of the ulna?",
    "options": [
      "Biceps brachii",
      "Brachialis",
      "Brachioradialis",
      "Triceps brachii"
    ],
    "topics": ["anatomy", "insertions", "muscle_origin_insertion"],
    "short_explanation": null,
    "long_explanation": null,
    "clinical_application": null,
    "source_reference": "Trail Guide to the Body",
    "filepath": "src/data/questions/anatomy/insertions/muscle_origin_insertion.json",
    "question_type": "multiple_choice",
    "difficulty": "Medium",
    "difficulty_rating": 3,
    "difficulty_adjustment": null,
    "relevance_score": null,
    "created_at": null,
    "updated_at": null,
    "tags": [
      "brachialis",
      "elbow",
      "insertion"
    ],
    "keywords": [
      "coronoid process",
      "ulna",
      "elbow flexor"
    ],
    "synonyms": null
  },
  {
    "id": "muscle_origin_insertion_006",
    "correctAnswer": "Semimembranosus",
    "question": "Which muscle originates on the ischial tuberosity and inserts on the medial condyle of the tibia?",
    "options": [
      "Semitendinosus",
      "Biceps femoris long head",
      "Semimembranosus",
      "Adductor magnus"
    ],
    "topics": ["anatomy", "insertions", "muscle_origin_insertion"],
    "short_explanation": null,
    "long_explanation": null,
    "clinical_application": null,
    "source_reference": "Moore's Clinically Oriented Anatomy",
    "filepath": "src/data/questions/anatomy/insertions/muscle_origin_insertion.json",
    "question_type": "multiple_choice",
    "difficulty": "Hard",
    "difficulty_rating": 4,
    "difficulty_adjustment": null,
    "relevance_score": null,
    "created_at": null,
    "updated_at": null,
    "tags": [
      "semimembranosus",
      "hamstrings",
      "origin insertion"
    ],
    "keywords": [
      "ischial tuberosity",
      "medial condyle",
      "knee flexion"
    ],
    "synonyms": null
  },
  {
    "id": "muscle_origin_insertion_007",
    "correctAnswer": "Greater tubercle of the humerus",
    "question": "The supraspinatus muscle originates from the supraspinous fossa of the scapula and inserts where?",
    "options": [
      "Greater tubercle of the humerus",
      "Acromion process",
      "Lesser tubercle of the humerus",
      "Coracoid process"
    ],
    "topics": ["anatomy", "insertions", "muscle_origin_insertion"],
    "short_explanation": null,
    "long_explanation": null,
    "clinical_application": null,
    "source_reference": "Kendall’s Muscles: Testing and Function",
    "filepath": "src/data/questions/anatomy/insertions/muscle_origin_insertion.json",
    "question_type": "multiple_choice",
    "difficulty": "Medium",
    "difficulty_rating": 3,
    "difficulty_adjustment": null,
    "relevance_score": null,
    "created_at": null,
    "updated_at": null,
    "tags": [
      "supraspinatus",
      "rotator cuff",
      "origin insertion"
    ],
    "keywords": [
      "greater tubercle",
      "shoulder abduction",
      "rotator cuff tear"
    ],
    "synonyms": null
  },
  {
    "id": "muscle_origin_insertion_008",
    "correctAnswer": "Coronoid process of the mandible",
    "question": "The temporalis muscle inserts on which structure?",
    "options": [
      "Zygomatic arch",
      "Coronoid process of the mandible",
      "Angle of the mandible",
      "Maxilla"
    ],
    "topics": ["anatomy", "insertions", "muscle_origin_insertion"],
    "short_explanation": null,
    "long_explanation": null,
    "clinical_application": null,
    "source_reference": "Gray’s Anatomy",
    "filepath": "src/data/questions/anatomy/insertions/muscle_origin_insertion.json",
    "question_type": "multiple_choice",
    "difficulty": "Medium",
    "difficulty_rating": 3,
    "difficulty_adjustment": null,
    "relevance_score": null,
    "created_at": null,
    "updated_at": null,
    "tags": [
      "temporalis",
      "jaw",
      "origin insertion"
    ],
    "keywords": [
      "mandible",
      "coronoid process",
      "TMJ"
    ],
    "synonyms": null
  },
  {
    "id": "muscle_origin_insertion_009",
    "correctAnswer": "Tensor fasciae latae",
    "question": "Which of the following muscles inserts into the iliotibial tract?",
    "options": [
      "Vastus lateralis",
      "Rectus femoris",
      "Tensor fasciae latae",
      "Gluteus maximus"
    ],
    "topics": ["anatomy", "insertions", "muscle_origin_insertion"],
    "short_explanation": null,
    "long_explanation": null,
    "clinical_application": null,
    "source_reference": "Trail Guide to the Body",
    "filepath": "src/data/questions/anatomy/insertions/muscle_origin_insertion.json",
    "question_type": "multiple_choice",
    "difficulty": "Medium",
    "difficulty_rating": 3,
    "difficulty_adjustment": null,
    "relevance_score": null,
    "created_at": null,
    "updated_at": null,
    "tags": [
      "TFL",
      "IT band",
      "hip"
    ],
    "keywords": [
      "tensor fasciae latae",
      "iliotibial tract",
      "hip movement"
    ],
    "synonyms": null
  },
  {
    "id": "muscle_origin_insertion_010",
    "correctAnswer": "Medial half of the clavicle",
    "question": "What is the origin of the pectoralis major's clavicular head?",
    "options": [
      "Sternal manubrium",
      "Lateral third of the clavicle",
      "Anterior surface of the sternum",
      "Medial half of the clavicle"
    ],
    "topics": ["anatomy", "insertions", "muscle_origin_insertion"],
    "short_explanation": null,
    "long_explanation": null,
    "clinical_application": null,
    "source_reference": "Moore's Clinically Oriented Anatomy",
    "filepath": "src/data/questions/anatomy/insertions/muscle_origin_insertion.json",
    "question_type": "multiple_choice",
    "difficulty": "Medium",
    "difficulty_rating": 3,
    "difficulty_adjustment": null,
    "relevance_score": null,
    "created_at": null,
    "updated_at": null,
    "tags": [
      "pectoralis major",
      "clavicle",
      "origin"
    ],
    "keywords": [
      "shoulder flexion",
      "chest muscle",
      "horizontal adduction"
    ],
    "synonyms": null
  }
]
